Metadata-Version: 2.1
Name: trxtools
Version: 0.3.3
Summary: Python tools facilitating bioinformatic analysis of nascent transcripts and transcriptomic data.
Author: Tomasz W. Turowski, Jan Mikołajczyk
Author-email: tomasz.turowski@ibb.waw.pl
License: LICENSE.txt
Keywords: bioinformatics RNA RNAfolding transcription BigWig
Classifier: Development Status :: 3 - Alpha
Classifier: Environment :: Console
Classifier: Intended Audience :: Science/Research
Classifier: License :: OSI Approved :: Apache Software License
Classifier: Operating System :: OS Independent
Classifier: Programming Language :: Python :: 3
Classifier: Topic :: Scientific/Engineering :: Bio-Informatics
Classifier: Topic :: Scientific/Engineering :: Visualization
Classifier: Topic :: Software Development :: Libraries :: Python Modules
Requires-Python: >=3.6
License-File: LICENSE.rst
Requires-Dist: scikit-learn
Requires-Dist: pandas
Requires-Dist: numpy
Requires-Dist: pybedtools
Requires-Dist: pyBigWig
Requires-Dist: adjustText
Requires-Dist: scipy
Requires-Dist: matplotlib_venn
Requires-Dist: seaborn
Requires-Dist: matplotlib
Requires-Dist: requests
